{"displayProperties": {"description": "Equip this ornament on any eligible Legendary armor item to change its appearance. Once you get a universal ornament, it's unlocked for all characters of the relevant class on your account.", "name": "Celestial Plate", "icon": "/common/destiny2_content/icons/cf11d768beac052e7082bc5e33e99c66.jpg", "hasIcon": true}, "scope": 0, "sourceString": "Source: Eververse", "sourceHash": 860688654, "itemHash": 2956050458, "acquisitionInfo": {"runOnlyAcquisitionRewardSite": false}, "stateInfo": {"requirements": {"entitlementUnavailableMessage": ""}}, "presentationNodeType": 1, "traitIds": [], "traitHashes": [], "parentNodeHashes": [3088345263], "hash": 1398890412, "index": 1503, "redacted": false, "blacklisted": false}