{"displayProperties": {"description": "", "name": "Empowered Finish", "icon": "/common/destiny2_content/icons/a8e2913f5e424d4c8ed18c719c85c2db.png", "iconSequences": [{"frames": ["/common/destiny2_content/icons/a8e2913f5e424d4c8ed18c719c85c2db.png"]}, {"frames": ["/common/destiny2_content/icons/cc346c28aa34a41a84fd8c9f5df45287.png"]}], "hasIcon": true}, "scope": 0, "sourceString": "Source: Earn rank-up packages from Banshee-44.", "sourceHash": 1788267693, "itemHash": 3632726236, "acquisitionInfo": {"runOnlyAcquisitionRewardSite": false}, "stateInfo": {"requirements": {"entitlementUnavailableMessage": ""}}, "presentationNodeType": 1, "traitIds": [], "traitHashes": [], "parentNodeHashes": [123185593], "hash": 1596314860, "index": 3088, "redacted": false, "blacklisted": false}