{"displayProperties": {"description": "", "name": "Crossroads Emblem", "icon": "/common/destiny2_content/icons/d0a17d93021cacb373d8a99d3130a84b.jpg", "hasIcon": true}, "scope": 0, "sourceString": "Source: Complete activities and earn rank-up packages on Mercury.", "sourceHash": 1654120320, "itemHash": 2939572589, "acquisitionInfo": {"runOnlyAcquisitionRewardSite": false}, "stateInfo": {"requirements": {"entitlementUnavailableMessage": ""}}, "presentationNodeType": 1, "traitIds": [], "traitHashes": [], "parentNodeHashes": [631010939], "hash": 225592289, "index": 3750, "redacted": false, "blacklisted": false}