{"displayProperties": {"description": "You can find this rare emblem once you reach a certain score in the Nightfall \"Insight Terminus.\"", "name": "Technocrat's Doom", "icon": "/common/destiny2_content/icons/0e48ed8a24cef0ff19c764aba6e33334.jpg", "hasIcon": true}, "scope": 0, "sourceString": "Source: Complete Nightfall strike \"The Insight Terminus.\"", "sourceHash": 3022766747, "itemHash": 3597022727, "acquisitionInfo": {"runOnlyAcquisitionRewardSite": false}, "stateInfo": {"requirements": {"entitlementUnavailableMessage": ""}}, "presentationNodeType": 1, "traitIds": [], "traitHashes": [], "parentNodeHashes": [3958514834], "hash": 2527097458, "index": 3672, "redacted": false, "blacklisted": false}