{"displayProperties": {"description": "", "name": "Taurus Rocketeer", "icon": "/common/destiny2_content/icons/fabee0ffe88e026d5dcee22b6829820e.jpg", "highResIcon": "/common/destiny2_content/icons/e15244071eb834f7f969e2974b09c03a.jpg", "hasIcon": true}, "scope": 0, "sourceString": "Source: Eververse", "sourceHash": 860688654, "itemHash": 1018723389, "acquisitionInfo": {"acquireMaterialRequirementHash": 1228020973, "runOnlyAcquisitionRewardSite": false}, "stateInfo": {"requirements": {"entitlementUnavailableMessage": ""}}, "presentationNodeType": 1, "traitIds": [], "traitHashes": [], "parentNodeHashes": [2079005400], "hash": 2534481771, "index": 4594, "redacted": false, "blacklisted": false}