{"displayProperties": {"description": "", "name": "Adept Blast Radius", "icon": "/common/destiny2_content/icons/c1c502dcc8b3fa6ce4277afc43fbdc11.jpg", "iconSequences": [{"frames": ["/common/destiny2_content/icons/c1c502dcc8b3fa6ce4277afc43fbdc11.jpg"]}, {"frames": ["/common/destiny2_content/icons/55c36e825a4ac05f3ea3620f50def66a.png"]}], "hasIcon": true}, "scope": 0, "sourceString": "Source: Flawless chest completion in the Trials of Osiris Lighthouse.", "sourceHash": 752988954, "itemHash": 229003538, "acquisitionInfo": {"runOnlyAcquisitionRewardSite": false}, "stateInfo": {"requirements": {"entitlementUnavailableMessage": ""}}, "presentationNodeType": 1, "traitIds": [], "traitHashes": [], "parentNodeHashes": [3839307707], "hash": 2895411254, "index": 3188, "redacted": false, "blacklisted": false}