{"displayProperties": {"description": "", "name": "Victory Lap", "icon": "/common/destiny2_content/icons/abd5903a6fff93f8410cec40fa5ae93e.jpg", "highResIcon": "/common/destiny2_content/icons/78579ab0ed55a975b01ee072b5e847ac.jpg", "hasIcon": true}, "scope": 0, "sourceString": "Source: Eververse", "sourceHash": 860688654, "itemHash": 1614326415, "acquisitionInfo": {"acquireMaterialRequirementHash": 2463837317, "runOnlyAcquisitionRewardSite": false}, "stateInfo": {"requirements": {"entitlementUnavailableMessage": ""}}, "presentationNodeType": 1, "traitIds": [], "traitHashes": [], "parentNodeHashes": [3030939313], "hash": 2974968120, "index": 4826, "redacted": false, "blacklisted": false}