{"displayProperties": {"description": "", "name": "Banshee Special", "icon": "/common/destiny2_content/icons/74cae4297a9f727468efef99db8321d2.png", "iconSequences": [{"frames": ["/common/destiny2_content/icons/74cae4297a9f727468efef99db8321d2.png"]}, {"frames": ["/common/destiny2_content/icons/b453d3f1ca72838214b66c8718568a92.png"]}], "hasIcon": true}, "scope": 0, "sourceString": "Source: Unlocked by default.", "sourceHash": 3083076965, "itemHash": 718367886, "acquisitionInfo": {"runOnlyAcquisitionRewardSite": false}, "stateInfo": {"requirements": {"entitlementUnavailableMessage": ""}}, "presentationNodeType": 1, "traitIds": [], "traitHashes": [], "parentNodeHashes": [3110461398], "hash": 3308648650, "index": 3221, "redacted": false, "blacklisted": false}