{"displayProperties": {"description": "This mod's effects stack with other copies of this mod.", "name": "Charged Up", "icon": "/common/destiny2_content/icons/ce29f32ba5ef8758d1b5f3cfad0944a6.png", "iconSequences": [{"frames": ["/common/destiny2_content/icons/ce29f32ba5ef8758d1b5f3cfad0944a6.png"]}, {"frames": ["/common/destiny2_content/icons/9a35202e9c71bb9f2029d5afec4b3427.png"]}], "hasIcon": true}, "scope": 0, "sourceString": "Source: Earn rank-up packages from Banshee-44.", "sourceHash": 1788267693, "itemHash": 3185435910, "acquisitionInfo": {"runOnlyAcquisitionRewardSite": false}, "stateInfo": {"requirements": {"entitlementUnavailableMessage": ""}}, "presentationNodeType": 1, "traitIds": [], "traitHashes": [], "parentNodeHashes": [123185593], "hash": 3551693174, "index": 3097, "redacted": false, "blacklisted": false}