{"displayProperties": {"description": "", "name": "Salvager's Salvo", "icon": "/common/destiny2_content/icons/e408748a790b4dee2789b1e7a234af89.jpg", "hasIcon": true}, "scope": 0, "sourceString": "Source: Salvager's Salvo Armament Quest", "sourceHash": 2986841134, "itemHash": 2060863616, "acquisitionInfo": {"acquireMaterialRequirementHash": 130662630, "runOnlyAcquisitionRewardSite": false}, "stateInfo": {"requirements": {"entitlementUnavailableMessage": ""}}, "presentationNodeType": 2, "traitIds": [], "traitHashes": [], "parentNodeHashes": [4089315591], "hash": 3768324462, "index": 4916, "redacted": false, "blacklisted": false}