{"displayProperties": {"description": "", "name": "Gigantes Shell", "icon": "/common/destiny2_content/icons/5b42ff47d5cd4c4dc233bb30214d0adf.jpg", "highResIcon": "/common/destiny2_content/icons/4dd1f5b9d0293c854734bd25df3b8c84.jpg", "hasIcon": true}, "scope": 0, "sourceString": "Source: Eververse", "sourceHash": 860688654, "itemHash": 2012043036, "acquisitionInfo": {"acquireMaterialRequirementHash": 4032750400, "runOnlyAcquisitionRewardSite": false}, "stateInfo": {"requirements": {"entitlementUnavailableMessage": ""}}, "presentationNodeType": 1, "traitIds": [], "traitHashes": [], "parentNodeHashes": [4000729534], "hash": 4222479895, "index": 2909, "redacted": false, "blacklisted": false}