{"displayProperties": {"description": "", "name": "Anamnesis", "icon": "/common/destiny2_content/icons/1a590790fda93ee4c57bcb624b3b615e.jpg", "hasIcon": true}, "scope": 0, "sourceString": "Source: Unlocked by a special offer.", "sourceHash": 1358645302, "itemHash": 3605490914, "acquisitionInfo": {"runOnlyAcquisitionRewardSite": false}, "stateInfo": {"requirements": {"entitlementUnavailableMessage": "Exclusive Item"}}, "presentationNodeType": 1, "traitIds": [], "traitHashes": [], "parentNodeHashes": [1166184619], "hash": 701980840, "index": 3450, "redacted": false, "blacklisted": false}